extensible_locks/__init__.py
extensible_locks-0.0.1.dist-info/LICENSE
extensible_locks-0.0.1.dist-info/METADATA
extensible_locks-0.0.1.dist-info/WHEEL
extensible_locks-0.0.1.dist-info/top_level.txt
extensible_locks-0.0.1.dist-info/RECORD
